Metadata-Version: 1.1
Name: PyBresenham
Version: 0.0.7
Summary: A Python module of generators that generate x, y coordinates for various vector shapes such as lines, rectangles, etc. Named after Bresenham of line-algorithm fame.
Home-page: https://github.com/asweigart/pybresenham
Author: Al Sweigart
Author-email: al@inventwithpython.com
License: BSD
Keywords: bresenham line circle drawing 2D geometry shapes vector bitmap rotate rotation vector2bitmap
Platform: UNKNOWN
Classifier: Development Status :: 4 - Beta
Classifier: Environment :: Win32 (MS Windows)
Classifier: Environment :: X11 Applications
Classifier: Environment :: MacOS X
Classifier: Intended Audience :: Developers
Classifier: License :: OSI Approved :: BSD License
Classifier: Operating System :: OS Independent
Classifier: Programming Language :: Python
Classifier: Programming Language :: Python :: 2
Classifier: Programming Language :: Python :: 2.5
Classifier: Programming Language :: Python :: 2.6
Classifier: Programming Language :: Python :: 2.7
Classifier: Programming Language :: Python :: 3
Classifier: Programming Language :: Python :: 3.1
Classifier: Programming Language :: Python :: 3.2
Classifier: Programming Language :: Python :: 3.3
Classifier: Programming Language :: Python :: 3.4
Classifier: Programming Language :: Python :: 3.5
Classifier: Programming Language :: Python :: 3.6
Classifier: Programming Language :: Python :: 3.7
Classifier: Programming Language :: Python :: 3.8
Classifier: Programming Language :: Python :: 3.9
